camo/__init__.py
camo/backend/__init__.py
camo/backend/conditional_independence_test.py
camo/backend/directed_graph.py
camo/backend/directed_markov_graph.py
camo/backend/graph.py
camo/backend/partial_ancestral_graph.py
camo/data/__init__.py
camo/data/adult.gz
camo/data/cd4.gz
camo/data/primer.py
camo/data/sprites.py
camo/discover/__init__.py
camo/discover/augmented_fci.py
camo/discover/ci.py
camo/discover/direct_lingam.py
camo/discover/fci.py
camo/discover/ica_lingam.py
camo/discover/pc.py
camo/estimate/__init__.py
camo/estimate/effects.py
camo/estimate/methods.py
camo/identify/__init__.py
camo/identify/backdoor_criterion.py
camo/identify/frontdoor_criterion.py
camo/structure/__init__.py
camo/structure/causal_model.py
camo/structure/linear_gaussian_scm.py
camo/structure/linear_nongaussian_scm.py
camo/structure/linear_scm.py
camo/structure/structural_causal_model.py
camo/utils/__init__.py
camo/utils/as_set.py
camo/utils/powerset.py
camo/utils/to_categorical.py
camo/utils/try_get.py
CaMo-0.0.5.dist-info/LICENSE
CaMo-0.0.5.dist-info/METADATA
CaMo-0.0.5.dist-info/WHEEL
CaMo-0.0.5.dist-info/top_level.txt
CaMo-0.0.5.dist-info/RECORD
