Metadata-Version: 2.1
Name: CaMo
Version: 0.0.5
Summary: CaMo: A Causal Model Library
Home-page: https://github.com/AlessioZanga/CaMo
Author: Alessio Zanga
Author-email: alessio.zanga@outlook.it
License: GNU GENERAL PUBLIC LICENSE - Version 3, 29 June 2007
Platform: Environment :: Console
Platform: Operating System :: POSIX :: Linux
Platform: Operating System :: Microsoft :: Windows :: Windows 10
Platform: Operating System :: MacOS
Classifier: Development Status :: 1 - Planning
Classifier: Intended Audience :: Science/Research
Classifier: License :: OSI Approved :: GNU General Public License v3 (GPLv3)
Classifier: Programming Language :: Python :: 3.6
Classifier: Programming Language :: Python :: 3.7
Classifier: Programming Language :: Python :: 3.8
Classifier: Programming Language :: Python :: 3.9
Classifier: Topic :: Scientific/Engineering :: Information Analysis
Classifier: Topic :: Software Development :: Libraries :: Python Modules
Requires-Dist: matplotlib
Requires-Dist: networkx (>=2.5)
Requires-Dist: numpy
Requires-Dist: pandas
Requires-Dist: scipy
Requires-Dist: scikit-learn
Requires-Dist: statsmodels
Requires-Dist: sympy
Requires-Dist: tqdm
